<theme>
<formatVersion>7</formatVersion>
<include>./../theme.xml</include>

<view name="basic, detailed, video">
    <text name="nameLabel" extra="true">
    <text>Visual Novel</text>
  </text>
</view>    

<view name="system">
  <text name="sys_line2" extra="true">
    <text>Visual Novel</text>
  </text>    
  <text name="shortdescription" extra="true">
   <text>Game Genre</text>
  </text>
  <text name="longdescription" extra="true">
   <text>A visual novel is an interactive fiction video game genre, featuring text-based story with narrative style of literature and interactivity aided by static or sprite-based visuals</text>
  </text>
 </view>
</theme>
